openrouter_selector/selector.py
openrouter_selector/＿init＿.py
openrouter_selector-0.0.3.dist-info/LICENSE
openrouter_selector-0.0.3.dist-info/METADATA
openrouter_selector-0.0.3.dist-info/WHEEL
openrouter_selector-0.0.3.dist-info/top_level.txt
openrouter_selector-0.0.3.dist-info/RECORD
