Metadata-Version: 2.1
Name: openrouter-selector
Version: 0.0.3
Summary: LLM connection using OpenRouter with a single library.
Author: kent
Project-URL: Homepage, https://github.com/KentHirose/openrouter-selector
Classifier: Programming Language :: Python :: 3
Classifier: License :: OSI Approved :: MIT License
Classifier: Operating System :: OS Independent
License-File: LICENSE
Requires-Dist: langchain >=0.1
